syncmux/__init__.py
syncmux/__main__.py
syncmux/cli.py
syncmux/daemon.py
syncmux/version.py
syncmux-0.1.1.dist-info/licenses/LICENSE
tests/__init__.py
tests/test_daemon.py
syncmux-0.1.1.dist-info/METADATA
syncmux-0.1.1.dist-info/WHEEL
syncmux-0.1.1.dist-info/entry_points.txt
syncmux-0.1.1.dist-info/top_level.txt
syncmux-0.1.1.dist-info/RECORD
