Metadata-Version: 2.4
Name: syncmux
Version: 0.1.1
Summary: Fast file synchronization for remote development over SSH
Home-page: https://github.com/bradley101/syncmux
Author: Shantanu Banerjee
Author-email: Shantanu Banerjee <shantanu@banerg.net>
License: MIT
Project-URL: Homepage, https://github.com/bradley101/syncmux
Project-URL: Repository, https://github.com/bradley101/syncmux
Keywords: ssh,sync,development,remote,rsync
Requires-Python: >=3.7
License-File: LICENSE
Requires-Dist: watchdog>=3.0.0
Dynamic: author
Dynamic: home-page
Dynamic: license-file
Dynamic: requires-python
